tinyurl_mcp_server/__init__.py
tinyurl_mcp_server/__main__.py
tinyurl_mcp_server/server.py
tinyurl_mcp_server-1.0.0.dist-info/METADATA
tinyurl_mcp_server-1.0.0.dist-info/WHEEL
tinyurl_mcp_server-1.0.0.dist-info/entry_points.txt
tinyurl_mcp_server-1.0.0.dist-info/licenses/LICENSE
tinyurl_mcp_server-1.0.0.dist-info/RECORD
