Metadata-Version: 2.4
Name: tinyurl-mcp-server
Version: 1.0.0
Summary: TinyURL MCP Server for generating short links
Project-URL: Homepage, https://github.com/sugarforever/tinyurl-mcp-server
Project-URL: Issues, https://github.com/sugarforever/tinyurl-mcp-server/issues
Author-email: VerySmallWoods <0001coder@gmail.com>
License: MIT
License-File: LICENSE
Classifier: Development Status :: 4 - Beta
Classifier: Intended Audience :: Developers
Classifier: License :: OSI Approved :: MIT License
Classifier: Programming Language :: Python :: 3
Classifier: Programming Language :: Python :: 3.12
Requires-Python: >=3.12
Requires-Dist: mcp>=1.6.0
Requires-Dist: requests>=2.32.3
